setup.py
ehcSdk/__init__.py
ehcSdk/cluster.py
ehcSdk/conn.py
ehcSdk/ehc_setting.py
ehcSdk.egg-info/PKG-INFO
ehcSdk.egg-info/SOURCES.txt
ehcSdk.egg-info/dependency_links.txt
ehcSdk.egg-info/top_level.txt
ehcSdk/utils/__init__.py
ehcSdk/utils/http_conn.py