Metadata-Version: 1.0
Name: ehcSdk
Version: 0.0.1
Summary: ehc python sdk
Home-page: UNKNOWN
Author: jingyue
Author-email: jingyue@zetyun.com
License: ehc License
Keywords: ehc,sdk
Platform: any
